llmling_models/__init__.py
llmling_models/__main__.py
llmling_models/auth/__init__.py
llmling_models/auth/anthropic_auth.py
llmling_models/auth/antigravity_auth.py
llmling_models/auth/gemini_auth.py
llmling_models/auth/github_auth.py
llmling_models/builtin_tools.py
llmling_models/formatting.py
llmling_models/git_hooks/__init__.py
llmling_models/git_hooks/ai_commit_message.py
llmling_models/log.py
llmling_models/model_types.py
llmling_models/models/__init__.py
llmling_models/models/augmented.py
llmling_models/models/claude_code_model.py
llmling_models/models/delegation.py
llmling_models/models/function_to_model.py
llmling_models/models/helpers.py
llmling_models/models/input_model/__init__.py
llmling_models/models/input_model/input_handlers.py
llmling_models/models/input_model/model.py
llmling_models/models/multi.py
llmling_models/models/pyodide_model.py
llmling_models/models/remote_input/__init__.py
llmling_models/models/remote_input/model.py
llmling_models/models/remote_input/server.py
llmling_models/models/remote_model/__init__.py
llmling_models/models/remote_model/model.py
llmling_models/models/remote_model/server.py
llmling_models/models/test_model.py
llmling_models/models/userselect.py
llmling_models/openai_server/__init__.py
llmling_models/openai_server/helpers.py
llmling_models/openai_server/models.py
llmling_models/openai_server/server.py
llmling_models/providers/__init__.py
llmling_models/providers/anthropic_max_provider.py
llmling_models/providers/copilot_provider.py
llmling_models/providers/lm_studio_provider.py
llmling_models/providers/moondream_provider.py
llmling_models/providers/requesty_provider.py
llmling_models/py.typed
llmling_models/scripts/get_copilot_api_key.py
llmling_models/tool_bridge.py
llmling_models/toolsets/__init__.py
llmling_models/toolsets/codemode_toolset.py
llmling_models/toolsets/helpers.py
llmling_models/utils.py
llmling_models_config/__init__.py
llmling_models_config/configs.py
llmling_models_config/py.typed
llmling_models-1.5.1.dist-info/licenses/LICENSE
llmling_models-1.5.1.dist-info/WHEEL
llmling_models-1.5.1.dist-info/entry_points.txt
llmling_models-1.5.1.dist-info/METADATA
llmling_models-1.5.1.dist-info/RECORD
