Metadata-Version: 2.4
Name: llmling-models
Version: 1.5.1
Summary: Pydantic-AI models for AgentPool
Keywords: 
Author: Philipp Temminghoff
Author-email: Philipp Temminghoff <philipptemminghoff@googlemail.com>
License-Expression: MIT
License-File: LICENSE
Classifier: Development Status :: 4 - Beta
Classifier: Framework :: Pydantic
Classifier: Framework :: Pydantic :: 2
Classifier: Intended Audience :: Developers
Classifier: Operating System :: OS Independent
Classifier: Programming Language :: Python :: 3
Classifier: Programming Language :: Python :: 3 :: Only
Classifier: Programming Language :: Python :: 3.12
Classifier: Programming Language :: Python :: 3.13
Classifier: Programming Language :: Python :: 3.14
Classifier: Topic :: Documentation
Classifier: Topic :: Software Development
Classifier: Topic :: Utilities
Classifier: Typing :: Typed
Requires-Dist: anyenv[httpx]
Requires-Dist: pydantic
Requires-Dist: pydantic-ai-slim>=1.27.0
Requires-Dist: schemez>=0.0.1
Requires-Dist: tokonomics>=0.4.0
Requires-Dist: claude-agent-sdk>=0.1.16 ; extra == 'claude'
Requires-Dist: fastmcp>=2.0.0 ; extra == 'codemode'
Requires-Dist: pydantic-ai ; extra == 'default'
Requires-Dist: openai ; extra == 'openai'
Requires-Dist: fastapi ; extra == 'remote'
Requires-Dist: uvicorn ; extra == 'remote'
Requires-Dist: websockets ; extra == 'remote'
Requires-Dist: uvicorn>=0.25.0 ; extra == 'server'
Requires-Dist: fastapi>=0.109.0 ; extra == 'server'
Requires-Dist: pyyaml>=6.0 ; extra == 'server'
Requires-Dist: websockets>=12.0 ; extra == 'server'
Requires-Dist: tokenizers ; extra == 'tokenizers'
Requires-Dist: transformers ; extra == 'transformers'
Requires-Python: >=3.13
Project-URL: Code coverage, https://app.codecov.io/gh/phil65/llmling-models
Project-URL: Discussions, https://github.com/phil65/llmling-models/discussions
Project-URL: Documentation, https://phil65.github.io/llmling-models/
Project-URL: Issues, https://github.com/phil65/llmling-models/issues
Project-URL: Source, https://github.com/phil65/llmling-models
Provides-Extra: claude
Provides-Extra: codemode
Provides-Extra: default
Provides-Extra: openai
Provides-Extra: remote
Provides-Extra: server
Provides-Extra: tokenizers
Provides-Extra: transformers
